MicceriRD/Data.py
MicceriRD/Sampling.py
MicceriRD/__init__.py
MicceriRD-0.2.dist-info/LICENSE.txt
MicceriRD-0.2.dist-info/METADATA
MicceriRD-0.2.dist-info/WHEEL
MicceriRD-0.2.dist-info/top_level.txt
MicceriRD-0.2.dist-info/RECORD
