Metadata-Version: 2.1
Name: MicceriRD
Version: 0.2
Summary: Real distributions identified by Ted Micceri in his seminal     1989 article: The Unicorn, The Normal Curve and Other Improbable Creatures - includes distributions and sampling functions.
Home-page: UNKNOWN
Author: Michael Lance
Author-email: michael.lance@gmail.com
License: UNKNOWN
Platform: UNKNOWN
Classifier: Programming Language :: Python :: 3
Classifier: License :: OSI Approved :: MIT License
Classifier: Operating System :: OS Independent
Requires-Python: >=3.0
